javascript_listener/__init__.py
javascript_listener/example.py
javascript_listener/frontend/build/asset-manifest.json
javascript_listener/frontend/build/bootstrap.min.css
javascript_listener/frontend/build/bootstrap.min.css.map
javascript_listener/frontend/build/index.html
javascript_listener/frontend/build/static/js/main.0cb66555.js
javascript_listener/frontend/build/static/js/main.0cb66555.js.LICENSE.txt
javascript_listener/frontend/build/static/js/main.0cb66555.js.map
streamlit_frontend_listener_component-0.0.9.dist-info/LICENSE
streamlit_frontend_listener_component-0.0.9.dist-info/METADATA
streamlit_frontend_listener_component-0.0.9.dist-info/WHEEL
streamlit_frontend_listener_component-0.0.9.dist-info/top_level.txt
streamlit_frontend_listener_component-0.0.9.dist-info/RECORD
